htmx_components/__init__.py
htmx_components/apps.py
htmx_components/tests.py
htmx_components/views.py
htmx_components/templates/htmx_components/form.html
htmx_components/templates/htmx_components/modal.html
htmx_components/templates/htmx_components/standalone.html
htmx_components-0.1.9.dist-info/licenses/LICENSE
htmx_components-0.1.9.dist-info/METADATA
htmx_components-0.1.9.dist-info/WHEEL
htmx_components-0.1.9.dist-info/top_level.txt
htmx_components-0.1.9.dist-info/RECORD
