Metadata-Version: 2.4
Name: htmx_components
Version: 0.1.9
Summary: Pre-defined components for htmx and Django.
Author-email: Frank Hennige <frank@hennige-it.de>
License-Expression: AGPL-3.0-or-later
Project-URL: Homepage, https://github.com/FrankHennige/htmx-components
Project-URL: Issues, https://github.com/FrankHennige/htmx-components/issues
Classifier: Programming Language :: Python :: 3
Classifier: Operating System :: OS Independent
Requires-Python: >=3.9
License-File: LICENSE
Requires-Dist: django-htmx>=1.26.0
Provides-Extra: build
Requires-Dist: uv~=0.8.24; extra == "build"
Dynamic: license-file
